{"C+": {"percentile_low": 0.13, "percent": 0.0, "numerator": 0, "percentile_high": 0.13}, "A": {"percentile_low": 0.74, "percent": 0.17, "numerator": 4, "percentile_high": 0.91}, "C": {"percentile_low": 0.13, "percent": 0.0, "numerator": 0, "percentile_high": 0.13}, "B": {"percentile_low": 0.26, "percent": 0.09, "numerator": 2, "percentile_high": 0.35}, "subtitle": "Working People in the Global Economy", "D": {"percentile_low": 0.0, "percent": 0.04, "numerator": 1, "percentile_high": 0.04}, "C-": {"percentile_low": 0.04, "percent": 0.09, "numerator": 2, "percentile_high": 0.13}, "title": "SOCIOL C116G", "B-": {"percentile_low": 0.13, "percent": 0.13, "numerator": 3, "percentile_high": 0.26}, "A+": {"percentile_low": 0.91, "percent": 0.09, "numerator": 2, "percentile_high": 1.0}, "denominator": 23, "A-": {"percentile_low": 0.48, "percent": 0.26, "numerator": 6, "percentile_high": 0.74}, "B+": {"percentile_low": 0.35, "percent": 0.13, "numerator": 3, "percentile_high": 0.48}, "F": {"percentile_low": 0.0, "percent": 0.0, "numerator": 0, "percentile_high": 0.0}, "section_letter": "B+", "course_id": 6910, "course_gpa": 3.243, "course_letter": "B+", "section_gpa": 3.243}