{"depart": "Earth and Planetary Science", "name": "Stratigraphy and Earth History", "prereq": ["Earth and Planetary Science 50", "Earth and Planetary Science 100A", "Earth and Planetary Science 100B"], "number": "115", "units": "4", "descrp": "Collecting, analyzing, and presenting stratigraphic data; dating and correlating sedimentary rocks; recognizing ancient environments and reconstructing Earth history; seismic and sequence stratigraphy; event stratigraphy and neocatastrophism; applications of stratigraphy to climate change, petroleum geology, and archaeology."}