{"units": "4.5", "descrp": "Psychophysical basis for clinical tests in acuity, perimetry, and color vision. The visual stimulus and photometry. Visual receptors. Psychophysical method and visual threshold. Light sensitivity. Contrast sensitivity. Light and dark adaptation. Temporal and spatial properties of visual function. Color vision and abnormalities. Changes with age and disease. Visual illusion. Basis for advanced diagnostic procedures.", "depart": "Vision Science", "number": "205", "name": "Visual Perception Sensitivity"}