{"C+": {"percentile_low": 0.18, "percent": 0.0, "numerator": 0, "percentile_high": 0.18}, "A": {"percentile_low": 0.73, "percent": 0.27, "numerator": 3, "percentile_high": 1.0}, "C": {"percentile_low": 0.09, "percent": 0.09, "numerator": 1, "percentile_high": 0.18}, "B": {"percentile_low": 0.27, "percent": 0.18, "numerator": 2, "percentile_high": 0.45}, "subtitle": "Scope and Methods of Research in Middle Eastern Studies", "D": {"percentile_low": 0.09, "percent": 0.0, "numerator": 0, "percentile_high": 0.09}, "C-": {"percentile_low": 0.09, "percent": 0.0, "numerator": 0, "percentile_high": 0.09}, "title": "M E STU 102", "B-": {"percentile_low": 0.18, "percent": 0.09, "numerator": 1, "percentile_high": 0.27}, "A+": {"percentile_low": 1.0, "percent": 0.0, "numerator": 0, "percentile_high": 1.0}, "denominator": 11, "A-": {"percentile_low": 0.55, "percent": 0.18, "numerator": 2, "percentile_high": 0.73}, "B+": {"percentile_low": 0.45, "percent": 0.09, "numerator": 1, "percentile_high": 0.55}, "F": {"percentile_low": 0.0, "percent": 0.09, "numerator": 1, "percentile_high": 0.09}, "section_letter": "B", "course_id": 4449, "course_gpa": 3.297, "course_letter": "B+", "section_gpa": 3.036}