{"depart": "History of Art", "name": "Teaching History of Art Pedagogy", "prereq": [], "number": "375", "units": "2", "descrp": "This pedagogical seminar introduces graduate students to methods and theories of teaching history of art. The course has two primary goals: (1) to train new graduate student instructors to assist in teaching History of Art classes at UCB; and (2) to introduce studnets to techniques of designing and teaching their own classes. The seminar may be taken concurrently with the first teaching assignment or in the semester before beginning teaching."}