{"depart": "Practice of Art", "name": "Bridging the Arts Seminar", "prereq": ["Dancers are encouraged to have taken Theater  166"], "number": "196", "units": "1-4", "descrp": " Bridging the Arts is open to artists from a variety of disciplines including dance, spoken word, theater, performance, creative writing, social practice, music, and visual arts. Through readings, written reflection, guest speakers, group discussion, and teaching in the field, Bridging the Arts (BtheArts) Student Instructors explore the arts in the public education system.  Student Instructors develop and implement arts curricula that is both age appropriate and culturally relevant to their students in underserved Bay Area Schools."}