{"depart": "Materials Science and Engineering", "name": "Thin", "prereq": ["Engineering  45", "Materials Science and Engineering 111"], "number": "125", "units": "3", "descrp": "Deposition, processing, and characterization of thin films and their technological applications. Physical and chemical vapor deposition methods. Thin-film nucleation and growth. Thermal and ion processing. Microstructural development in epitaxial, polycrystalline, and amorphous films. Thin-film characterization techniques. Applications in information storage, integrated circuits, and optoelectronic devices. Laboratory demonstrations."}