{"depart": "Information", "name": "Information Organization Laboratory", "prereq": ["It is recommended that students take  202"], "number": "290TA", "units": "3", "descrp": "Students will build tools to explore and apply theories of information organization and retrieval. Students will implement various concepts covered in the concurrent 202 course through small projects on topics like controlled vocabularies, the semantic web, and corpus analysis. We will also experiment with topics suggested by students during the course. Students will develop skills in rapid prototyping of web-based projects using Python, XML, and jQuery."}