{"C+": {"percentile_low": 0.03, "percent": 0.03, "numerator": 5, "percentile_high": 0.05}, "A": {"percentile_low": 0.91, "percent": 0.09, "numerator": 17, "percentile_high": 1.0}, "C": {"percentile_low": 0.02, "percent": 0.01, "numerator": 1, "percentile_high": 0.03}, "B": {"percentile_low": 0.14, "percent": 0.22, "numerator": 41, "percentile_high": 0.36}, "subtitle": "Antebellum America: The Advent of Mass Society", "D": {"percentile_low": 0.02, "percent": 0.01, "numerator": 1, "percentile_high": 0.02}, "C-": {"percentile_low": 0.02, "percent": 0.0, "numerator": 0, "percentile_high": 0.02}, "F": {"percentile_low": 0.0, "percent": 0.02, "numerator": 3, "percentile_high": 0.02}, "B-": {"percentile_low": 0.05, "percent": 0.09, "numerator": 17, "percentile_high": 0.14}, "course_gpa": 3.292, "denominator": 190, "A-": {"percentile_low": 0.65, "percent": 0.26, "numerator": 49, "percentile_high": 0.91}, "B+": {"percentile_low": 0.36, "percent": 0.29, "numerator": 56, "percentile_high": 0.65}, "title": "HISTORY 122AC", "section_letter": "B+", "course_id": 3606, "A+": {"percentile_low": 1.0, "percent": 0.0, "numerator": 0, "percentile_high": 1.0}, "course_letter": "B+", "section_gpa": 3.252}