{"C+": {"percentile_low": 0.0, "percent": 0.0, "numerator": 0, "percentile_high": 0.0}, "A": {"percentile_low": 0.63, "percent": 0.32, "numerator": 12, "percentile_high": 0.95}, "C": {"percentile_low": 0.0, "percent": 0.0, "numerator": 0, "percentile_high": 0.0}, "B": {"percentile_low": 0.0, "percent": 0.08, "numerator": 3, "percentile_high": 0.08}, "subtitle": "Foundation Engineering Design", "D": {"percentile_low": 0.0, "percent": 0.0, "numerator": 0, "percentile_high": 0.0}, "C-": {"percentile_low": 0.0, "percent": 0.0, "numerator": 0, "percentile_high": 0.0}, "title": "CIV ENG 177", "B-": {"percentile_low": 0.0, "percent": 0.0, "numerator": 0, "percentile_high": 0.0}, "A+": {"percentile_low": 0.95, "percent": 0.05, "numerator": 2, "percentile_high": 1.0}, "denominator": 38, "A-": {"percentile_low": 0.34, "percent": 0.29, "numerator": 11, "percentile_high": 0.63}, "B+": {"percentile_low": 0.08, "percent": 0.26, "numerator": 10, "percentile_high": 0.34}, "F": {"percentile_low": 0.0, "percent": 0.0, "numerator": 0, "percentile_high": 0.0}, "section_letter": "A-", "course_id": 1382, "course_gpa": 3.441, "course_letter": "B+", "section_gpa": 3.65}