{"depart": "Chinese", "name": "Readings in Chinese Buddhist Texts", "prereq": [], "number": "C140", "units": "4", "descrp": "This course is an introduction to the study of medieval Buddhist literature written in classical Chinese. We will read samples from a variety of genres, including early Chinese translations of Sanskrit and Central Asian Buddhist scriptures, indigenous Chinese commentaries, philosophical treatises, and sectarian works, including Chan gongan (Zen koans). The course will also serve as an introduction to resource materials used in the study of Chinese Buddhist texts, and students will be expected to make use of a variety of reference tools in preparation for class. Readings in Chinese will be supplemented by a range of secondary readings in English on Mahayana doctrine and Chinese Buddhist history. Also listed as Group in Buddhist Studies C140."}