{"units": "3", "descrp": "Exploration of common origins of urban planning and public health, from why and how the fields separated and strategies to reconnect them, to addressing urban health inequities in the 21st century. Inquiry to influences of urban population health, analysis of determinants, and roles that city planning and public health agencies - at local and international level - have in research, and action aimed at improving urban health. Measures, analysis, and design of policy strategies are explored.", "depart": "City and Regional Planning", "number": "256", "name": "Healthy Cities"}