{"depart": "International and Area Studies", "name": "Intermediate Microeconomic Theory", "prereq": ["Economics  1"], "number": "206", "units": "4", "descrp": "This course is designed as a comprehensive overview of intermediate microeconomic theory. It covers a number of topics including consumer and demand theory, firm, production, and cost theory, competitive market theory, imperfect competition, welfare economics, choice under uncertainity, and information. All analysis conducted in the course relies on graphical and algebraic techniques. Outside reading and discussion sections will demonstrate the applicability of the models covered in class to topics with an international dimension, such as the setting of tariffs, cartel behavior, and international trade."}