{"C+": {"percentile_low": 0.0, "percent": 0.04, "numerator": 1, "percentile_high": 0.04}, "A": {"percentile_low": 0.46, "percent": 0.46, "numerator": 11, "percentile_high": 0.92}, "C": {"percentile_low": 0.0, "percent": 0.0, "numerator": 0, "percentile_high": 0.0}, "B": {"percentile_low": 0.04, "percent": 0.04, "numerator": 1, "percentile_high": 0.08}, "subtitle": "Politics and Culture in 20th-Century Germany: A Century of Extremes", "D": {"percentile_low": 0.0, "percent": 0.0, "numerator": 0, "percentile_high": 0.0}, "C-": {"percentile_low": 0.0, "percent": 0.0, "numerator": 0, "percentile_high": 0.0}, "title": "GERMAN 160A", "B-": {"percentile_low": 0.04, "percent": 0.0, "numerator": 0, "percentile_high": 0.04}, "A+": {"percentile_low": 0.92, "percent": 0.08, "numerator": 2, "percentile_high": 1.0}, "denominator": 24, "A-": {"percentile_low": 0.13, "percent": 0.33, "numerator": 8, "percentile_high": 0.46}, "B+": {"percentile_low": 0.08, "percent": 0.04, "numerator": 1, "percentile_high": 0.13}, "F": {"percentile_low": 0.0, "percent": 0.0, "numerator": 0, "percentile_high": 0.0}, "section_letter": "A-", "course_id": 3320, "course_gpa": 3.701, "course_letter": "A-", "section_gpa": 3.758}