{"C+": {"numerator": 0, "percent": 0.0, "percentile_low": 0.0, "percentile_high": 0.0}, "A": {"numerator": 7, "percent": 0.33, "percentile_low": 0.62, "percentile_high": 0.95}, "C": {"numerator": 0, "percent": 0.0, "percentile_low": 0.0, "percentile_high": 0.0}, "B": {"numerator": 1, "percent": 0.05, "percentile_low": 0.0, "percentile_high": 0.05}, "subtitle": "Twentieth-Century Harmony", "D": {"numerator": 0, "percent": 0.0, "percentile_low": 0.0, "percentile_high": 0.0}, "C-": {"numerator": 0, "percent": 0.0, "percentile_low": 0.0, "percentile_high": 0.0}, "F": {"numerator": 0, "percent": 0.0, "percentile_low": 0.0, "percentile_high": 0.0}, "B-": {"numerator": 0, "percent": 0.0, "percentile_low": 0.0, "percentile_high": 0.0}, "course_gpa": 3.491, "title": "MUSIC 151", "A-": {"numerator": 11, "percent": 0.52, "percentile_low": 0.1, "percentile_high": 0.62}, "denominator": 21, "B+": {"numerator": 1, "percent": 0.05, "percentile_low": 0.05, "percentile_high": 0.1}, "section_letter": "A-", "course_id": 5106, "A+": {"numerator": 1, "percent": 0.05, "percentile_low": 0.95, "percentile_high": 1.0}, "course_letter": "B+", "section_gpa": 3.762}