{"depart": "Undergraduate Business Administration", "name": "Behavioral Finance", "prereq": ["Undergraduate Business Administration 103"], "number": "136F", "units": "3", "descrp": "This course looks at the influence of decision heuristics and biases on investor welfare, financial markets, and corporate decisions. Topics include overconfidence, attribution theory, representative heuristic, availability heuristic, anchoring and adjustment, prospect theory, \"Winner's Curse,\" speculative bubbles, IPOs, market efficiency, limits of arbitrage, relative mis-pricing of common stocks, the tendency to trade in a highly correlated fashion, investor welfare, and market anomalies."}