{"units": "1", "descrp": "This course is an advanced alcohol research seminar in which presentations are made by alcohol research scientists nationally and internationally, as well as pre-and post-doctoral fellows, and focus on special topical areas related to psychosocial research in the field each semester. Areas covered include the epidemiology of drinking patterns and alcohol-related problems, issues related to treatment of alcohol-related problems, and health services research. Guest presentations are also provided (related to topics outside psychosocial research) to provide a breadth of understanding in the field. The seminar also includes sessions focused on methodological issues in alcohol-related research and grant writing, and has a research ethics component covering a number of sessions.", "depart": "Public Health", "number": "202G", "name": "Advanced Alcohol Research Seminar"}