{"units": "4", "descrp": "This course examines the history of indigenous, aboriginal, native, or \"tribal\" peoples over the last five centuries. Particular attention is paid to how these groups were brought into relations with an expanding Europe, capitalist development, and modern nation-states. How have these peoples survived, what are the contemporary challenges they face, and what resources and allies have they drawn on in the present? Also listed as Native American Studies C73AC.", "depart": "Ethnic Studies", "number": "C73AC", "name": "Indigenous Peoples in Global Inequality"}