{"depart": "Sociology", "name": "The Power of Numbers", "prereq": ["Sociology 1", "Sociology 3", "Sociology 3AC"], "number": "7", "units": "4", "descrp": "This course will provide students with a set of skills to understand, evaluate, use, and produce quantitative data about the social world. It is intended specifically for social science majors, and focuses on social science questions. Students will learn to: produce basic graphs, find good-quality and relevant data on the web, manipulate data in a spreadsheet, including producing pivot tables, understand and calculate basic statistical measures of central tendency, variation, and correlation, understand and apply basic concepts of sampling and selection, and recognize an impossible statistic."}